pnap_invoicing_api/__init__.py
pnap_invoicing_api/api_client.py
pnap_invoicing_api/api_response.py
pnap_invoicing_api/configuration.py
pnap_invoicing_api/exceptions.py
pnap_invoicing_api/py.typed
pnap_invoicing_api/rest.py
pnap_invoicing_api/version.py
pnap_invoicing_api/api/__init__.py
pnap_invoicing_api/api/invoices_api.py
pnap_invoicing_api/models/__init__.py
pnap_invoicing_api/models/error.py
pnap_invoicing_api/models/invoice.py
pnap_invoicing_api/models/paginated_invoices.py
pnap_invoicing_api/models/paginated_response.py
pnap_invoicing_api-1.0.4.dist-info/METADATA
pnap_invoicing_api-1.0.4.dist-info/WHEEL
pnap_invoicing_api-1.0.4.dist-info/top_level.txt
pnap_invoicing_api-1.0.4.dist-info/RECORD
